composio_client/__init__.py
composio_client/_base_client.py
composio_client/_client.py
composio_client/_compat.py
composio_client/_constants.py
composio_client/_exceptions.py
composio_client/_files.py
composio_client/_models.py
composio_client/_qs.py
composio_client/_resource.py
composio_client/_response.py
composio_client/_streaming.py
composio_client/_types.py
composio_client/_version.py
composio_client/py.typed
composio_client/_utils/__init__.py
composio_client/_utils/_compat.py
composio_client/_utils/_datetime_parse.py
composio_client/_utils/_logs.py
composio_client/_utils/_proxy.py
composio_client/_utils/_reflection.py
composio_client/_utils/_resources_proxy.py
composio_client/_utils/_streams.py
composio_client/_utils/_sync.py
composio_client/_utils/_transform.py
composio_client/_utils/_typing.py
composio_client/_utils/_utils.py
composio_client/lib/.keep
composio_client/resources/__init__.py
composio_client/resources/auth_configs.py
composio_client/resources/cli.py
composio_client/resources/connected_accounts.py
composio_client/resources/files.py
composio_client/resources/link.py
composio_client/resources/migration.py
composio_client/resources/toolkits.py
composio_client/resources/tools.py
composio_client/resources/triggers_types.py
composio_client/resources/mcp/__init__.py
composio_client/resources/mcp/custom.py
composio_client/resources/mcp/generate.py
composio_client/resources/mcp/mcp.py
composio_client/resources/project/__init__.py
composio_client/resources/project/config.py
composio_client/resources/project/project.py
composio_client/resources/tool_router/__init__.py
composio_client/resources/tool_router/session.py
composio_client/resources/tool_router/tool_router.py
composio_client/resources/trigger_instances/__init__.py
composio_client/resources/trigger_instances/manage.py
composio_client/resources/trigger_instances/trigger_instances.py
composio_client/types/__init__.py
composio_client/types/auth_config_create_params.py
composio_client-1.26.0.dist-info/METADATA
composio_client-1.26.0.dist-info/WHEEL
composio_client-1.26.0.dist-info/licenses/LICENSE
composio_client-1.26.0.dist-info/RECORD
